{
  "timestamp": "2025-08-13T21:52:31.225534",
  "agent": "producer",
  "phase": "user_feedback_processing",
  "status": "CRITICAL_ISSUES_IDENTIFIED",
  "user_feedback": {
    "route_optimizer_issues": [
      "\u274c CRITICAL: Add button adds 2 stops at a time instead of 1",
      "\u274c CRITICAL: Optimize button does nothing - no calculation occurs",
      "\u274c CRITICAL: Google Maps not displaying in Route Optimizer",
      "\u274c CRITICAL: After deleting all stops, Add button stops working",
      "\u274c STYLING: Route optimization card has color contrast issues"
    ],
    "mileage_calculator_issues": [
      "\u274c CRITICAL: Adding firm button does not work",
      "\u274c CRITICAL: Calculate mileage button does not click or display anything",
      "\u2705 WORKING: Dropdown functionality works properly"
    ],
    "authentication_issues": [
      "\u274c CRITICAL: Login screen inputs don't accept text (email/password)",
      "\u274c CRITICAL: Drop In/Sign Up buttons don't function",
      "\u274c CRITICAL: Drop In button shows spinning display but doesn't work",
      "\u274c CRITICAL: Hover and click functions not working",
      "\u2705 WORKING: Dashboard redirect to login screen works"
    ]
  },
  "agent_assignments": {
    "lyricist_agent_tasks": [
      "\ud83c\udfb5 FIX: Route Optimizer Add Stop button - should add only 1 stop",
      "\ud83c\udfb5 FIX: Route Optimizer Optimize button - implement calculation logic",
      "\ud83c\udfb5 FIX: Route Optimizer state management - fix Add button after deletion",
      "\ud83c\udfb5 FIX: Mileage Calculator Adding Firm button functionality",
      "\ud83c\udfb5 FIX: Mileage Calculator Calculate button click events",
      "\ud83c\udfb5 FIX: Login form input fields - enable text entry",
      "\ud83c\udfb5 FIX: Login form button click handlers and submission"
    ],
    "security_agent_tasks": [
      "\ud83d\udd12 FIX: Google Maps integration - maps not displaying",
      "\ud83d\udd12 FIX: Google Maps API initialization in Route Optimizer",
      "\ud83d\udd12 DEBUG: Authentication system form handlers",
      "\ud83d\udd12 FIX: Login form event listeners and validation"
    ],
    "designer_agent_tasks": [
      "\ud83c\udfa8 FIX: Route optimization card color contrast issues",
      "\ud83c\udfa8 STYLE: Login form input field styling and interaction states",
      "\ud83c\udfa8 POLISH: Button hover states and visual feedback",
      "\ud83c\udfa8 REVIEW: Overall color consistency across modules"
    ]
  },
  "execution_plan": {
    "phase_1_immediate": [
      "\ud83c\udfb5 Lyricist Agent: Fix Add Stop button duplication issue",
      "\ud83c\udfb5 Lyricist Agent: Fix Optimize button calculation logic",
      "\ud83d\udd12 Security Agent: Restore Google Maps display",
      "\ud83c\udfb5 Lyricist Agent: Fix login form input functionality"
    ],
    "phase_2_critical": [
      "\ud83c\udfb5 Lyricist Agent: Fix Mileage Calculator buttons",
      "\ud83d\udd12 Security Agent: Debug authentication system",
      "\ud83c\udfb5 Lyricist Agent: Fix Route Optimizer state management"
    ],
    "phase_3_polish": [
      "\ud83c\udfa8 Designer Agent: Fix color contrast issues",
      "\ud83c\udfa8 Designer Agent: Enhance button interactions",
      "\ud83c\udfc6 Final quality assurance testing"
    ]
  },
  "priority": {
    "severity": "CRITICAL - Multiple core functions broken",
    "impact": "HIGH - User cannot complete primary workflows",
    "urgency": "IMMEDIATE - Requires all-hands agent coordination",
    "estimated_fixes": "15 tasks across 3 agents",
    "success_criteria": "All Add/Calculate/Login functions working properly"
  },
  "total_critical_issues": 10,
  "total_tasks": 15
}